{
  "include": [
    "whatstk"
  ],
  "exclude": [
    "**/__pycache__",
    "**/.pytest_cache",
    "**/node_modules",
    ".venv",
    "build",
    "dist"
  ],
  "pythonVersion": "3.11",
  "pythonPlatform": "All",
  "typeCheckingMode": "basic",
  "reportMissingImports": true,
  "reportMissingTypeStubs": false,
  "reportUnusedImport": false,
  "reportUnusedClass": false,
  "reportUnusedFunction": false,
  "reportUnusedVariable": false,
  "reportDuplicateImport": true,
  "reportOptionalSubscript": false,
  "reportOptionalMemberAccess": false,
  "reportOptionalCall": false,
  "reportOptionalIterable": false,
  "reportOptionalContextManager": false,
  "reportOptionalOperand": false,
  "reportTypedDictNotRequiredAccess": false,
  "reportPrivateImportUsage": false,
  "reportConstantRedefinition": true,
  "reportIncompatibleMethodOverride": false,
  "reportIncompatibleVariableOverride": true,
  "reportUntypedFunctionDecorator": false,
  "reportUntypedClassDecorator": false,
  "reportUntypedBaseClass": false,
  "reportUntypedNamedTuple": false,
  "reportGeneralTypeIssues": false,
  "reportArgumentType": false,
  "reportReturnType": false,
  "reportAttributeAccessIssue": false,
  "reportAssignmentType": false,
  "reportIndexIssue": false,
  "reportCallIssue": false,
  "reportOperatorIssue": false,
  "reportUnhashable": false
}
